setup.py
pp_jinja2/__init__.py
pypoly_plugin_jinja.egg-info/PKG-INFO
pypoly_plugin_jinja.egg-info/SOURCES.txt
pypoly_plugin_jinja.egg-info/dependency_links.txt
pypoly_plugin_jinja.egg-info/entry_points.txt
pypoly_plugin_jinja.egg-info/not-zip-safe
pypoly_plugin_jinja.egg-info/requires.txt
pypoly_plugin_jinja.egg-info/top_level.txt