Metadata-Version: 1.0
Name: pypoly-plugin-jinja
Version: 0.1
Summary: Use Jinja2 in PyPoly applications
Home-page: UNKNOWN
Author: PyPoly Team
Author-email: UNKNOWN
License: UNKNOWN
Platform: UNKNOWN
Classifier: Development Status :: 3 - Alpha
Classifier: License :: OSI Approved :: GNU General Public License (GPL)
Classifier: License :: OSI Approved :: MIT License
Classifier: Programming Language :: Python
Classifier: Topic :: Internet :: WWW/HTTP :: Dynamic Content
